Metadata-Version: 2.4
Name: hyperpod_checkpointless_training
Version: 100.0.0
Summary: HyperPod CHE verification training package
Home-page: https://github.com/chehaoha/hyperpod-checkpointless-training
Author: hp-eng
Author-email: hp-eng@amazon.com
License: Apache License 2.0
Classifier: Programming Language :: Python :: 3
Classifier: License :: OSI Approved :: Apache Software License
Classifier: Operating System :: OS Independent
Requires-Python: >=3.6
License-File: LICENSE.txt
Dynamic: author
Dynamic: author-email
Dynamic: classifier
Dynamic: description
Dynamic: description-content-type
Dynamic: home-page
Dynamic: license
Dynamic: license-file
Dynamic: requires-python
Dynamic: summary
